{"Reviews": [], "ProductInfo": {"Price": "$444.95", "Features": "KIT INCLUDES 11 PRODUCTS -- All BRAND NEW Items with all Manufacturer-supplied Accessories + Full USA Warranties:\n<1> Olympus Tough TG-2 iHS Shock & Waterproof Digital Camera (Black) + <2> PD-DCM Compact Camera Case +\n<3> Transcend 16GB Class 4 SD Card + <4> Spare Li-90B Battery + <5> PD-T14 Flexible Camera Tripod +\n<6> Floating Foam Camera Strap + <7> PD Memory Card Storage Wallet + <8> PD SDHC Memory Card Reader +\n<9> LCD Monitor Screen Protectors + <10> PD 5pc Complete Cleaning Kit + <11> Image Recovery Software", "Name": "Olympus Tough TG-2 iHS Shock & Waterproof Digital Camera (Black) with 16GB Card + Case + Battery + Flex Tripod + Accessory Kit", "ImgURL": "http://ecx.images-amazon.com/images/I/61AZy5qpI6L._SY300_.jpg", "ProductID": "B00B77U366"}}